{
  "ContentNavigator": {
    "description": "Auto imported from components/global/ContentNavigator.vue"
  },
  "DeleteConfirmationDialog": {
    "description": "Auto imported from components/global/DeleteConfirmationDialog.vue"
  },
  "FavoriteButton": {
    "description": "Auto imported from components/global/FavoriteButton.vue"
  },
  "NormalHeader": {
    "description": "Auto imported from components/global/NormalHeader.vue"
  },
  "ShowSnackbar": {
    "description": "Auto imported from components/global/ShowSnackbar.vue"
  },
  "SpecialHeader": {
    "description": "Auto imported from components/global/SpecialHeader.vue"
  },
  "SubmitButton": {
    "description": "Auto imported from components/global/SubmitButton.vue"
  }
}
